docbrowser/__init__.py
docbrowser/browser.py
docbrowser-0.0.0.dist-info/LICENSE
docbrowser-0.0.0.dist-info/METADATA
docbrowser-0.0.0.dist-info/WHEEL
docbrowser-0.0.0.dist-info/top_level.txt
docbrowser-0.0.0.dist-info/RECORD
