Metadata-Version: 2.1
Name: docbrowser
Version: 0.0.0
Summary: A cli-based app for reading Markdown project docs
Author-email: Nick Veitch <nick.veitch@canonical.com>
Project-URL: Homepage, https://github.com/evilnick/docbrowser
Project-URL: Issues, https://github.com/evilnick/docbrowser/issues
Classifier: Programming Language :: Python :: 3
Classifier: License :: OSI Approved :: GNU General Public License v3 or later (GPLv3+)
Classifier: Operating System :: OS Independent
Classifier: Development Status :: 1 - Planning
Requires-Python: >=3.8
License-File: LICENSE
